README.txt
setup.py
TGCombine.egg-info/PKG-INFO
TGCombine.egg-info/SOURCES.txt
TGCombine.egg-info/dependency_links.txt
TGCombine.egg-info/not-zip-safe
TGCombine.egg-info/paster_plugins.txt
TGCombine.egg-info/requires.txt
TGCombine.egg-info/sqlobject.txt
TGCombine.egg-info/top_level.txt
tgcombine/__init__.py
tgcombine/combine.py
tgcombine/jsmin.py
tgcombine/jspacker.py
tgcombine/release.py
