Metadata-Version: 1.0
Name: TGCombine
Version: 1.0.4
Summary: Turbogears Javascript/CSS Combine and Pack
Home-page: http://tgcombine.googlecode.com
Author: Vince Spicer
Author-email: vinces1979@gmail.com
License: MIT
Keywords: turbogears.widgets
Platform: UNKNOWN
Classifier: Development Status :: 3 - Alpha
Classifier: Operating System :: OS Independent
Classifier: Programming Language :: Python
Classifier: Topic :: Software Development :: Libraries :: Python Modules
Classifier: Framework :: TurboGears
Classifier: Framework :: TurboGears :: Widgets
